{
  "variants": {
    "facing=south,part=head": { "model": "littlecraft:block/crib_head_blue" },
    "facing=west,part=head":  { "model": "littlecraft:block/crib_head_blue", "y": 90 },
    "facing=north,part=head": { "model": "littlecraft:block/crib_head_blue", "y": 180 },
    "facing=east,part=head":  { "model": "littlecraft:block/crib_head_blue", "y": 270 },
    "facing=south,part=foot": { "model": "littlecraft:block/crib_foot_blue" },
    "facing=west,part=foot":  { "model": "littlecraft:block/crib_foot_blue", "y": 90 },
    "facing=north,part=foot": { "model": "littlecraft:block/crib_foot_blue", "y": 180 },
    "facing=east,part=foot":  { "model": "littlecraft:block/crib_foot_blue", "y": 270 }
  }
}
